[
  { "id": "kirie_default", "name": "Default", "category": "portrait", "image": "images/kirie_default.png", "layer": "portrait", "removeWhiteBackground": true, "tags": ["default"] },
  { "id": "kirie_variant", "name": "Variant", "category": "portrait", "image": "images/kirie_variant.png", "layer": "portrait", "removeWhiteBackground": true, "tags": ["variant"] },
  { "id": "bra_black", "name": "Black Bra", "category": "bra", "image": "images/bra_black.jpg", "layer": "underwear", "removeWhiteBackground": true, "tags": ["black"] },
  { "id": "bra_pink", "name": "Pink Bra", "category": "bra", "image": "images/bra_pink.png", "layer": "underwear", "tags": ["pink"] },
  { "id": "bra_risky", "name": "Risky Swimsuit", "category": "bra", "image": "images/bra_risky.png", "layer": "underwear", "tags": ["swimsuit", "strap"] },
  { "id": "pants_black", "name": "Black Underwear", "category": "pants", "image": "images/pants_black.jpg", "layer": "underwear", "removeWhiteBackground": true, "tags": ["black"] },
  { "id": "pants_pink", "name": "Pink Shorts", "category": "pants", "image": "images/pants_pink.png", "layer": "underwear", "tags": ["pink"] },
  { "id": "dress_pink", "name": "Pink Dress", "category": "dress", "image": "images/dress_pink.jpg", "layer": "costume", "removeWhiteBackground": true, "tags": ["pink", "dress"] },
  { "id": "dress_offshoulder_pink", "name": "Off-Shoulder Pink Dress", "category": "dress", "image": "images/dress_offshoulder_pink.png", "layer": "costume", "removeWhiteBackground": true, "tags": ["pink", "dress"] },
  { "id": "top_maid", "name": "Maid Top", "category": "tops", "image": "images/top_maid.png", "layer": "costume", "removeWhiteBackground": true, "tags": ["maid", "black"] },
  { "id": "top_sailor", "name": "Sailor Top", "category": "tops", "image": "images/top_sailor.png", "layer": "costume", "tags": ["sailor", "white"] },
  { "id": "top_racequeen", "name": "Race Queen Top", "category": "tops", "image": "images/top_racequeen.png", "layer": "costume", "tags": ["racequeen", "red"], "hideLayers": ["armsFront"] },
  { "id": "top_police", "name": "Police Top", "category": "tops", "image": "images/top_police.png", "layer": "costume", "tags": ["police", "navy"] },
  { "id": "top_gothic", "name": "Gothic Top", "category": "tops", "image": "images/top_gothic.png", "layer": "costume", "tags": ["gothic", "black"] },
  { "id": "skirt_maid", "name": "Maid Skirt", "category": "skirt", "image": "images/skirt_maid.png", "layer": "costume", "removeWhiteBackground": true, "tags": ["maid", "black"] },
  { "id": "skirt_navy_chain", "name": "Navy Chain Skirt", "category": "skirt", "image": "images/skirt_navy_chain.png", "layer": "costume", "tags": ["navy", "sailor"] },
  { "id": "skirt_racequeen", "name": "Race Queen Shorts", "category": "skirt", "image": "images/skirt_racequeen.png", "layer": "costume", "tags": ["racequeen", "red"] },
  { "id": "skirt_police", "name": "Police Skirt", "category": "skirt", "image": "images/skirt_police.png", "layer": "costume", "tags": ["police", "navy"] },
  { "id": "skirt_gothic", "name": "Gothic Skirt", "category": "skirt", "image": "images/skirt_gothic.png", "layer": "costume", "tags": ["gothic", "black"] },
  { "id": "socks_white", "name": "White Socks", "category": "socks", "image": "images/socks_white.png", "layer": "legwear", "removeWhiteBackground": true, "tags": ["white"] },
  { "id": "socks_black", "name": "Black Socks", "category": "socks", "image": "images/socks_black.png", "layer": "legwear", "tags": ["black"] },
  { "id": "socks_racequeen", "name": "Race Queen Boots", "category": "socks", "image": "images/socks_racequeen.png", "layer": "legwear", "tags": ["racequeen", "red", "boots"] },
  { "id": "socks_police", "name": "Police Legwear", "category": "socks", "image": "images/socks_police.png", "layer": "legwear", "tags": ["police", "black"] },
  { "id": "outer_leather_jacket", "name": "Leather Jacket", "category": "outer", "image": "images/outer_leather_jacket.jpg", "layer": "outerwear", "removeWhiteBackground": true, "tags": ["black", "jacket"], "hideLayers": ["armsFront"], "offsetY": -234 },
  { "id": "arms_front", "name": "Arms Front", "category": "armOverlay", "image": "images/kirie_arms_front.png", "layer": "armsFront", "removeWhiteBackground": true, "tags": ["arms"] },
  { "id": "hat_police", "name": "Police Hat", "category": "hat", "image": "images/hat_police.png", "layer": "headwear", "tags": ["police", "navy"] }
]
